LICENSE-2.0.txt
README.md
pyproject.toml
requirements.txt
cwl2nx/__init__.py
cwl2nx/__main__.py
cwl2nx/cli.py
cwl2nx/cwl2nx.py
cwl2nx/term_viz.py
cwl2nx.egg-info/PKG-INFO
cwl2nx.egg-info/SOURCES.txt
cwl2nx.egg-info/dependency_links.txt
cwl2nx.egg-info/entry_points.txt
cwl2nx.egg-info/requires.txt
cwl2nx.egg-info/top_level.txt