Metadata-Version: 2.4
Name: cwl2nx
Version: 0.0.11
Summary: Lightweight python module to load, validate and visualize CWL (Common Workflow Language) files through networkx graphs.
Author-email: Marius Garénaux Gruau <marius.garenaux-gruau@irisa.fr>
Maintainer-email: Marius Garénaux Gruau <marius.garenaux-gruau@irisa.fr>
License-Expression: Apache-2.0
Project-URL: Repository, https://github.com/mariusgarenaux/cwl2nx
Keywords: cwl,workflow,graphs,networkx,visualization
Classifier: Programming Language :: Python :: 3
Classifier: Operating System :: OS Independent
Requires-Python: >=3.12
License-File: LICENSE-2.0.txt
Requires-Dist: backports.tarfile==1.2.0
Requires-Dist: cwl-utils==0.40
Requires-Dist: filelock==3.19.1
Requires-Dist: importlib-metadata==8.0.0
Requires-Dist: inflect==7.3.1
Requires-Dist: jaraco-functools==4.3.0
Requires-Dist: jaraco.collections==5.1.0
Requires-Dist: matplotlib==3.10.6
Requires-Dist: networkx==3.5
Requires-Dist: pandas==2.3.2
Requires-Dist: platformdirs==4.2.2
Requires-Dist: pyyaml==6.0.2
Requires-Dist: scipy==1.16.2
Requires-Dist: termcolor==3.1.0
Requires-Dist: tomli==2.0.1
Requires-Dist: typer==0.19.2
Dynamic: license-file
